ppqi/__init__.py
ppqi/inference.py
ppqi-1.0.4.dist-info/LICENSE
ppqi-1.0.4.dist-info/METADATA
ppqi-1.0.4.dist-info/WHEEL
ppqi-1.0.4.dist-info/top_level.txt
ppqi-1.0.4.dist-info/RECORD
