Metadata-Version: 2.1
Name: ppqi
Version: 1.0.4
Summary: Paddle Quick Inference
Home-page: UNKNOWN
Author: jm12138
Author-email: 2286040843@qq.com
License: Apache-2.0 License
Platform: UNKNOWN
